{
  "date": "2026-04-24",
  "noBetDay": false,
  "noBetReason": "",
  "flat": [
    {
      "time": "15:35",
      "course": "Sandown",
      "type": "flat",
      "distance": "1m2f",
      "going": "good",
      "runners": 7,
      "horses": [
        {
          "num": 3,
          "name": "ACTION",
          "jockey": "R. L. Moore",
          "trainer": "A. P. O'Brien",
          "odds": 2.38,
          "prevOdds": 2.5,
          "tipsters": 5,
          "formStr": "3132-",
          "goingWins": 2,
          "goingRuns": 4,
          "courseWins": 0,
          "distanceWins": 1,
          "trainerInForm": true,
          "rpr": 115,
          "confidence": "high",
          "reason": "Multiple tipsters have named this Aidan O'Brien-trained colt as their best bet in the Group 3 Classic Trial. He went close in the Futurity at Doncaster last season and is bred to excel as he steps up to middle distances. Ryan Moore in the saddle is always a positive, and Ballydoyle have won this race before with their Derby candidates.",
          "result": "",
          "position": 0
        }
      ]
    },
    {
      "time": "13:50",
      "course": "Sandown",
      "type": "flat",
      "distance": "1m",
      "going": "good",
      "runners": 7,
      "horses": [
        {
          "num": 2,
          "name": "NOBODY KNOWS",
          "jockey": "W. Buick",
          "trainer": "J. & T. Gosden",
          "odds": 3.75,
          "prevOdds": 4.5,
          "tipsters": 4,
          "formStr": "11-",
          "goingWins": 2,
          "goingRuns": 2,
          "courseWins": 0,
          "distanceWins": 1,
          "trainerInForm": true,
          "rpr": 95,
          "confidence": "high",
          "reason": "This Gosden-trained colt arrives unbeaten in two career starts and the bookmakers have shortened his price all morning. Racing Post tips say his ceiling has yet to be ascertained, suggesting there's more to come. With William Buick taking the ride in the Esher Cup Handicap, the connections clearly mean business.",
          "result": "",
          "position": 0
        }
      ]
    },
    {
      "time": "13:20",
      "course": "Sandown",
      "type": "flat",
      "distance": "5f",
      "going": "good",
      "runners": 14,
      "horses": [
        {
          "num": 9,
          "name": "HYPNOTISED",
          "jockey": "J. Watson",
          "trainer": "R. Varian",
          "odds": 5.0,
          "prevOdds": 5.5,
          "tipsters": 3,
          "formStr": "1-",
          "goingWins": 1,
          "goingRuns": 1,
          "courseWins": 0,
          "distanceWins": 0,
          "trainerInForm": true,
          "rpr": 88,
          "confidence": "medium",
          "reason": "Timeform highlighted this Roger Varian-trained colt as one to watch. He was impressive winning at Southwell last autumn and this mark looks within range on his reappearance. The stable is well-versed with these types of sprinters and the price offers decent value in a competitive sprint handicap.",
          "result": "",
          "position": 0
        }
      ]
    }
  ],
  "jumps": [
    {
      "time": "14:05",
      "course": "Perth",
      "type": "chase",
      "distance": "3m6f",
      "going": "good",
      "runners": 11,
      "horses": [
        {
          "num": 4,
          "name": "FEVER DREAM",
          "jockey": "B. Hughes",
          "trainer": "D. Skelton",
          "odds": 4.33,
          "prevOdds": 5.0,
          "tipsters": 4,
          "formStr": "1P212",
          "goingWins": 2,
          "goingRuns": 5,
          "courseWins": 0,
          "distanceWins": 1,
          "trainerInForm": true,
          "rpr": 125,
          "confidence": "high",
          "reason": "The market leader in the QuinnBet Highland National has been well-backed all morning. Dan Skelton is poised to be crowned Champion Trainer and his string is in flying form. This staying chaser handles good ground well and the booking of Brian Hughes - one of the top northern-based jockeys - is a strong signal of intent.",
          "result": "",
          "position": 0
        }
      ]
    },
    {
      "time": "14:40",
      "course": "Perth",
      "type": "hurdle",
      "distance": "3m2f",
      "going": "good",
      "runners": 12,
      "horses": [
        {
          "num": 5,
          "name": "JUPITER DES MOTTES",
          "jockey": "H. Cobden",
          "trainer": "P. Nicholls",
          "odds": 4.0,
          "prevOdds": 4.5,
          "tipsters": 4,
          "formStr": "1121P",
          "goingWins": 2,
          "goingRuns": 4,
          "courseWins": 0,
          "distanceWins": 2,
          "trainerInForm": true,
          "rpr": 130,
          "confidence": "high",
          "reason": "Racing Post and multiple sources identify this Paul Nicholls runner as the one to beat in the Perth Racecourse Handicap Hurdle. He's unexposed over staying trips and the yard knows what it takes to win the big handicaps. Harry Cobden is in excellent form and the price has been shortening steadily.",
          "result": "",
          "position": 0
        }
      ]
    },
    {
      "time": "16:20",
      "course": "Chepstow",
      "type": "hurdle",
      "distance": "2m4f",
      "going": "good to soft",
      "runners": 10,
      "horses": [
        {
          "num": 3,
          "name": "TESTING PATIENCE",
          "jockey": "S. Bowen",
          "trainer": "O. Murphy",
          "odds": 2.63,
          "prevOdds": 3.0,
          "tipsters": 3,
          "formStr": "21121",
          "goingWins": 3,
          "goingRuns": 5,
          "courseWins": 1,
          "distanceWins": 2,
          "trainerInForm": true,
          "rpr": 128,
          "confidence": "medium",
          "reason": "This Olly Murphy-trained hurdler has been in fine form and Sean Bowen takes the ride at a track where he boasts a strong record. The horse has shown he handles cut in the ground and arrives here with solid claims in the novices' hurdle. The price has shortened which suggests stable confidence.",
          "result": "",
          "position": 0
        }
      ]
    }
  ],
  "results": {
    "flat": [
      {
        "position": 0,
        "result": "",
        "winReturn": 0,
        "placeReturn": 0,
        "totalReturn": 0
      },
      {
        "position": 0,
        "result": "",
        "winReturn": 0,
        "placeReturn": 0,
        "totalReturn": 0
      },
      {
        "position": 0,
        "result": "",
        "winReturn": 0,
        "placeReturn": 0,
        "totalReturn": 0
      }
    ],
    "jumps": [
      {
        "position": 0,
        "result": "",
        "winReturn": 0,
        "placeReturn": 0,
        "totalReturn": 0
      },
      {
        "position": 0,
        "result": "",
        "winReturn": 0,
        "placeReturn": 0,
        "totalReturn": 0
      },
      {
        "position": 0,
        "result": "",
        "winReturn": 0,
        "placeReturn": 0,
        "totalReturn": 0
      }
    ],
    "patentReturn": 0,
    "patentProfit": 0,
    "complete": false
  }
}